[
    {
        "trial_number": 0,
        "part_name": "Baseline RNN",
        "model_name": "LM_RNN",
        "parameters": {
            "n_epochs": 100,
            "patience_value": 5,
            "hid_size": 250,
            "emb_size": 400,
            "optimizer": "SGD",
            "lr": 4.0,
            "clip": 5.0,
            "train_batch_size": 64,
            "eval_batch_size": 128
        },
        "eval_ppl": 230.15442834200402,
        "best_val_loss": 5.48101648655038
    },
    {
        "trial_number": 1,
        "part_name": "Baseline RNN",
        "model_name": "LM_RNN",
        "parameters": {
            "n_epochs": 100,
            "patience_value": 5,
            "hid_size": 200,
            "emb_size": 350,
            "optimizer": "SGD",
            "lr": 0.01,
            "clip": 5.0,
            "train_batch_size": 64,
            "eval_batch_size": 128
        },
        "eval_ppl": 285.9473842435966,
        "best_val_loss": 5.684592385392989
    },
    {
        "trial_number": 2,
        "part_name": "Baseline RNN",
        "model_name": "LM_RNN",
        "parameters": {
            "n_epochs": 100,
            "patience_value": 5,
            "hid_size": 400,
            "emb_size": 500,
            "optimizer": "SGD",
            "lr": 2.0,
            "clip": 5.0,
            "train_batch_size": 64,
            "eval_batch_size": 128
        },
        "eval_ppl": 179.04297727266206,
        "best_val_loss": 5.222482656616263
    },
    {
        "trial_number": 3,
        "part_name": "Baseline RNN",
        "model_name": "LM_RNN",
        "parameters": {
            "n_epochs": 100,
            "patience_value": 5,
            "hid_size": 250,
            "emb_size": 350,
            "optimizer": "SGD",
            "lr": 0.5,
            "clip": 5.0,
            "train_batch_size": 64,
            "eval_batch_size": 128
        },
        "eval_ppl": 154.37781115194664,
        "best_val_loss": 5.087424645557341
    },
    {
        "trial_number": 4,
        "part_name": "Baseline RNN",
        "model_name": "LM_RNN",
        "parameters": {
            "n_epochs": 100,
            "patience_value": 5,
            "hid_size": 300,
            "emb_size": 300,
            "optimizer": "SGD",
            "lr": 1.0,
            "clip": 5.0,
            "train_batch_size": 64,
            "eval_batch_size": 128
        },
        "eval_ppl": 158.73368588615477,
        "best_val_loss": 5.114905529127895
    },
    {
        "trial_number": 5,
        "part_name": "Baseline RNN",
        "model_name": "LM_RNN",
        "parameters": {
            "n_epochs": 100,
            "patience_value": 5,
            "hid_size": 300,
            "emb_size": 400,
            "optimizer": "SGD",
            "lr": 0.5,
            "clip": 5.0,
            "train_batch_size": 64,
            "eval_batch_size": 128
        },
        "eval_ppl": 152.7495980041968,
        "best_val_loss": 5.076219183966117
    },
    {
        "trial_number": 6,
        "part_name": "Baseline RNN",
        "model_name": "LM_RNN",
        "parameters": {
            "n_epochs": 100,
            "patience_value": 5,
            "hid_size": 300,
            "emb_size": 350,
            "optimizer": "SGD",
            "lr": 0.01,
            "clip": 5.0,
            "train_batch_size": 64,
            "eval_batch_size": 128
        },
        "eval_ppl": 262.7064397118539,
        "best_val_loss": 5.599109523170017
    },
    {
        "trial_number": 7,
        "part_name": "Baseline RNN",
        "model_name": "LM_RNN",
        "parameters": {
            "n_epochs": 100,
            "patience_value": 5,
            "hid_size": 300,
            "emb_size": 500,
            "optimizer": "SGD",
            "lr": 3.0,
            "clip": 5.0,
            "train_batch_size": 64,
            "eval_batch_size": 128
        },
        "eval_ppl": 211.8766511324268,
        "best_val_loss": 5.391188177863954
    },
    {
        "trial_number": 8,
        "part_name": "Baseline RNN",
        "model_name": "LM_RNN",
        "parameters": {
            "n_epochs": 100,
            "patience_value": 5,
            "hid_size": 400,
            "emb_size": 450,
            "optimizer": "SGD",
            "lr": 0.1,
            "clip": 5.0,
            "train_batch_size": 64,
            "eval_batch_size": 128
        },
        "eval_ppl": 155.32164277324648,
        "best_val_loss": 5.091838391739327
    },
    {
        "trial_number": 9,
        "part_name": "Baseline RNN",
        "model_name": "LM_RNN",
        "parameters": {
            "n_epochs": 100,
            "patience_value": 5,
            "hid_size": 300,
            "emb_size": 300,
            "optimizer": "SGD",
            "lr": 0.05,
            "clip": 5.0,
            "train_batch_size": 64,
            "eval_batch_size": 128
        },
        "eval_ppl": 171.70166110441164,
        "best_val_loss": 5.187195231755664
    },
    {
        "trial_number": 10,
        "part_name": "Baseline RNN",
        "model_name": "LM_RNN",
        "parameters": {
            "n_epochs": 100,
            "patience_value": 5,
            "hid_size": 350,
            "emb_size": 400,
            "optimizer": "SGD",
            "lr": 5.0,
            "clip": 5.0,
            "train_batch_size": 64,
            "eval_batch_size": 128
        },
        "eval_ppl": 925.8404838433609,
        "best_val_loss": 6.839461463031858
    },
    {
        "trial_number": 12,
        "part_name": "Baseline RNN",
        "model_name": "LM_RNN",
        "parameters": {
            "n_epochs": 100,
            "patience_value": 5,
            "hid_size": 250,
            "emb_size": 400,
            "optimizer": "SGD",
            "lr": 0.5,
            "clip": 5.0,
            "train_batch_size": 64,
            "eval_batch_size": 128
        },
        "eval_ppl": 152.6228615349098,
        "best_val_loss": 5.085813261937953
    },
    {
        "trial_number": 13,
        "part_name": "Baseline RNN",
        "model_name": "LM_RNN",
        "parameters": {
            "n_epochs": 100,
            "patience_value": 5,
            "hid_size": 200,
            "emb_size": 400,
            "optimizer": "SGD",
            "lr": 0.5,
            "clip": 5.0,
            "train_batch_size": 64,
            "eval_batch_size": 128
        },
        "eval_ppl": 154.92787243393389,
        "best_val_loss": 5.094375636798107
    },
    {
        "trial_number": 14,
        "part_name": "Baseline RNN",
        "model_name": "LM_RNN",
        "parameters": {
            "n_epochs": 100,
            "patience_value": 5,
            "hid_size": 350,
            "emb_size": 400,
            "optimizer": "SGD",
            "lr": 0.5,
            "clip": 5.0,
            "train_batch_size": 64,
            "eval_batch_size": 128
        },
        "eval_ppl": 153.11752412486194,
        "best_val_loss": 5.0711385755922365
    },
    {
        "trial_number": 16,
        "part_name": "Baseline RNN",
        "model_name": "LM_RNN",
        "parameters": {
            "n_epochs": 100,
            "patience_value": 5,
            "hid_size": 350,
            "emb_size": 450,
            "optimizer": "SGD",
            "lr": 5.0,
            "clip": 5.0,
            "train_batch_size": 64,
            "eval_batch_size": 128
        },
        "eval_ppl": 1914.3170400775443,
        "best_val_loss": 7.5582652162838295
    },
    {
        "trial_number": 17,
        "part_name": "Baseline RNN",
        "model_name": "LM_RNN",
        "parameters": {
            "n_epochs": 100,
            "patience_value": 5,
            "hid_size": 350,
            "emb_size": 400,
            "optimizer": "SGD",
            "lr": 2.0,
            "clip": 5.0,
            "train_batch_size": 64,
            "eval_batch_size": 128
        },
        "eval_ppl": 177.43463834421215,
        "best_val_loss": 5.216880109645813
    },
    {
        "trial_number": 18,
        "part_name": "Baseline RNN",
        "model_name": "LM_RNN",
        "parameters": {
            "n_epochs": 100,
            "patience_value": 5,
            "hid_size": 300,
            "emb_size": 400,
            "optimizer": "SGD",
            "lr": 4.0,
            "clip": 5.0,
            "train_batch_size": 64,
            "eval_batch_size": 128
        },
        "eval_ppl": 254.87748436419162,
        "best_val_loss": 5.593419052277934
    },
    {
        "trial_number": 19,
        "part_name": "Baseline RNN",
        "model_name": "LM_RNN",
        "parameters": {
            "n_epochs": 100,
            "patience_value": 5,
            "hid_size": 350,
            "emb_size": 400,
            "optimizer": "SGD",
            "lr": 0.1,
            "clip": 5.0,
            "train_batch_size": 64,
            "eval_batch_size": 128
        },
        "eval_ppl": 156.56803441698884,
        "best_val_loss": 5.095341745542691
    },
    {
        "trial_number": 20,
        "part_name": "Baseline RNN",
        "model_name": "LM_RNN",
        "parameters": {
            "n_epochs": 100,
            "patience_value": 5,
            "hid_size": 200,
            "emb_size": 500,
            "optimizer": "SGD",
            "lr": 1.0,
            "clip": 5.0,
            "train_batch_size": 64,
            "eval_batch_size": 128
        },
        "eval_ppl": 155.25617365447562,
        "best_val_loss": 5.095581356438237
    },
    {
        "trial_number": 23,
        "part_name": "Baseline RNN",
        "model_name": "LM_RNN",
        "parameters": {
            "n_epochs": 100,
            "patience_value": 5,
            "hid_size": 400,
            "emb_size": 400,
            "optimizer": "SGD",
            "lr": 0.5,
            "clip": 5.0,
            "train_batch_size": 64,
            "eval_batch_size": 128
        },
        "eval_ppl": 154.34604278173526,
        "best_val_loss": 5.07462521864789
    }
]